gmlp_tinygrad/__init__.py
gmlp_tinygrad-0.9.2.dist-info/LICENSE
gmlp_tinygrad-0.9.2.dist-info/METADATA
gmlp_tinygrad-0.9.2.dist-info/WHEEL
gmlp_tinygrad-0.9.2.dist-info/top_level.txt
gmlp_tinygrad-0.9.2.dist-info/RECORD
