Metadata-Version: 2.1
Name: gmlp-tinygrad
Version: 0.9.2
Summary: An implementation of gated MLPs in tinygrad, as an alternative to transformers.
Author: Ethan Bennett
Classifier: Programming Language :: Python :: 3
Classifier: License :: OSI Approved :: MIT License
Classifier: Operating System :: OS Independent
Requires-Python: >=3.8
License-File: LICENSE
Requires-Dist: tinygrad
Requires-Dist: einops
Requires-Dist: numpy
